{
  "orchestration_manifest": {
    "sequence": [
      {
        "name": "setup_dev_environment",
        "arguments": {
          "project": "atlas-core",
          "language": "python",
          "dependencies": ["requests", "fastapi"]
        }
      },
      {
        "name": "dependency_scan",
        "arguments": {
          "path": "/projects/atlas-core",
          "tool": "safety",
          "severity": "high"
        }
      },
      {
        "name": "prepare_lab_simulation",
        "arguments": {
          "lab_profile": "isolation-net",
          "topology": "docker_compose"
        }
      },
      {
        "name": "run_vulnerability_scan",
        "arguments": {
          "target": "localhost",
          "scan_profile": "full",
          "authorization_token": "[REDACTED_LAB_AUTH]"
        }
      },
      {
        "name": "create_remediation_patch",
        "arguments": {
          "vuln_id": "VULN-001",
          "repo_path": "/projects/atlas-core"
        }
      }
    ],
    "summary": "End-to-end DevSecOps orchestration: scaffold, dependency scan, isolated lab simulation, vulnerability scan, and remediation patch generation.",
    "audit": {
      "actor": "NEXUS-LEGION X OMEGA",
      "timestamp": "2025-11-02T03:30:00Z",
      "authorization_provided": "[REDACTED_LAB_AUTH]"
    }
  }
}
